brucelee/__init__.py
brucelee/_loader.py
brucelee/_utils.py
brucelee/auth.py
brucelee/base_controller.py
brucelee/cbv.py
brucelee/config.py
brucelee/controller.py
brucelee/controller_utils.py
brucelee/core.py
brucelee/database.py
brucelee/midware.py
brucelee/midware_casbin.py
brucelee/midware_session.py
brucelee/view.py
brucelee/scripts/__init__.py
brucelee/scripts/_app.py
brucelee/scripts/_controller.py
brucelee/scripts/_project.py
brucelee/scripts/_run.py
brucelee/scripts/main.py
brucelee/scripts/tpls/app/controller.tpl
brucelee/scripts/tpls/app/css.tpl
brucelee/scripts/tpls/app/home.css.tpl
brucelee/scripts/tpls/app/home.tpl
brucelee/scripts/tpls/app/model.tpl
brucelee/scripts/tpls/app/service.tpl
brucelee/scripts/tpls/app/test.tpl
brucelee/scripts/tpls/app/view.tpl
brucelee/scripts/tpls/project/.gitignore
brucelee/scripts/tpls/project/main.py
brucelee/scripts/tpls/project/apps/__init__.py
brucelee/scripts/tpls/project/configs/alembic.ini
brucelee/scripts/tpls/project/configs/cache.yaml
brucelee/scripts/tpls/project/configs/casbin-adapter.csv
brucelee/scripts/tpls/project/configs/casbin-model.conf
brucelee/scripts/tpls/project/configs/database.yaml
brucelee/scripts/tpls/project/configs/general.yaml
brucelee/scripts/tpls/project/configs/session.yaml
brucelee/scripts/tpls/project/public/error_404.html
brucelee/scripts/tpls/project/public/error_500.html
brucelee-1.1.0.data/scripts/main.py
brucelee-1.1.0.dist-info/METADATA
brucelee-1.1.0.dist-info/WHEEL
brucelee-1.1.0.dist-info/entry_points.txt
brucelee-1.1.0.dist-info/top_level.txt
brucelee-1.1.0.dist-info/RECORD
