Metadata-Version: 2.1
Name: brucelee
Version: 1.1.0
Summary: Simple and elegant use of FastApi in MVC mode
Home-page: https://github.com/smjkzsl/brucelee
Author: Bruce chou
Author-email: smjkzsl@gmail.com
License: Apache License 2.0
Keywords: web framework,mvc framework,fastapi framework
Classifier: License :: OSI Approved :: Apache Software License
Classifier: Operating System :: OS Independent
Classifier: Programming Language :: Python :: 3.6
Classifier: Programming Language :: Python :: 3.7
Classifier: Programming Language :: Python :: 3.8
Classifier: Programming Language :: Python :: 3.9
Classifier: Programming Language :: Python :: 3.10
Classifier: Programming Language :: Python :: 3.11
Requires-Python: >=3.6
Requires-Dist: alembic (==1.10.3)
Requires-Dist: anyio (==3.6.2)
Requires-Dist: async-timeout (==4.0.2)
Requires-Dist: casbin (==1.18.0)
Requires-Dist: certifi (==2022.12.7)
Requires-Dist: charset-normalizer (==3.1.0)
Requires-Dist: click (==8.1.3)
Requires-Dist: colorama (==0.4.6)
Requires-Dist: dnspython (==2.3.0)
Requires-Dist: docopt (==0.6.2)
Requires-Dist: fastapi (==0.95.1)
Requires-Dist: greenlet (==2.0.2)
Requires-Dist: gunicorn (==20.1.0)
Requires-Dist: h11 (==0.14.0)
Requires-Dist: httptools (==0.5.0)
Requires-Dist: idna (==3.4)
Requires-Dist: inflect (==6.0.4)
Requires-Dist: itsdangerous (==2.1.2)
Requires-Dist: Jinja2 (==3.1.2)
Requires-Dist: Mako (==1.2.4)
Requires-Dist: MarkupSafe (==2.1.2)
Requires-Dist: multipart (==0.2.4)
Requires-Dist: mypy-extensions (==1.0.0)
Requires-Dist: pipreqs (==0.4.13)
Requires-Dist: pydantic (==1.10.2)
Requires-Dist: PyJWT (==2.6.0)
Requires-Dist: pymongo (==3.6.0)
Requires-Dist: python-dotenv (==1.0.0)
Requires-Dist: python-multipart (==0.0.6)
Requires-Dist: PyYAML (==6.0)
Requires-Dist: redis (==4.5.4)
Requires-Dist: requests (==2.28.2)
Requires-Dist: simpleeval (==0.9.13)
Requires-Dist: sniffio (==1.3.0)
Requires-Dist: SQLAlchemy (==2.0.9)
Requires-Dist: starlette (==0.26.1)
Requires-Dist: typing-extensions (==4.5.0)
Requires-Dist: typing-inspect (==0.8.0)
Requires-Dist: ujson (==5.5.0)
Requires-Dist: urllib3 (==1.26.15)
Requires-Dist: uvicorn (==0.21.1)
Requires-Dist: watchfiles (==0.19.0)
Requires-Dist: websockets (==11.0.2)
Requires-Dist: yarg (==0.1.9)
Requires-Dist: chardet (==5.1.0)
Requires-Dist: pusher (==3.3.2)
